coastal_dynamics/__init__.py
coastal_dynamics/factory.py
coastal_dynamics/format_testing.ipynb
coastal_dynamics/geometries.py
coastal_dynamics/industry.py
coastal_dynamics/io.py
coastal_dynamics/modify_notebooks.py
coastal_dynamics/multiple_choice.py
coastal_dynamics/multiple_selection.py
coastal_dynamics/numeric.py
coastal_dynamics/question.py
coastal_dynamics/text.py
coastal_dynamics/use_answers_app.py
coastal_dynamics/utils.py
coastal_dynamics-1.0.1.dist-info/LICENSE
coastal_dynamics-1.0.1.dist-info/METADATA
coastal_dynamics-1.0.1.dist-info/WHEEL
coastal_dynamics-1.0.1.dist-info/RECORD
