Metadata-Version: 2.3
Name: coastal-dynamics
Version: 1.0.1
Summary: Python package for Coastal Dynamics at Delft University of Technology
License: BSD
Author: TU Delft Coastal Dynamics
Author-email: j.bosboom@tudelft.nl
Requires-Python: >=3.11,<4.0
Classifier: License :: Other/Proprietary License
Classifier: Programming Language :: Python :: 3
Classifier: Programming Language :: Python :: 3.11
Classifier: Programming Language :: Python :: 3.12
Classifier: Programming Language :: Python :: 3.13
Requires-Dist: pytest (>=7.4.0,<8.0.0)
